abdm_gateway/__init__.py
abdm_gateway/api/__init__.py
abdm_gateway/api/cm_facing_api.py
abdm_gateway/api/consent_flow_api.py
abdm_gateway/api/data_flow_api.py
abdm_gateway/api/discovery_api.py
abdm_gateway/api/hip_facing_api.py
abdm_gateway/api/hiu_facing_api.py
abdm_gateway/api/identification_api.py
abdm_gateway/api/link_api.py
abdm_gateway/api/monitoring_api.py
abdm_gateway/api/patient_notification_api.py
abdm_gateway/api/profile_api.py
abdm_gateway/api/services_api.py
abdm_gateway/api/sessions_api.py
abdm_gateway/api/subscriptions_api.py
abdm_gateway/api/user_auth_api.py
abdm_gateway/api_client.py
abdm_gateway/api_response.py
abdm_gateway/configuration.py
abdm_gateway/exceptions.py
abdm_gateway/models/__init__.py
abdm_gateway/models/access_token_validity.py
abdm_gateway/models/auth_confirm_identifier.py
abdm_gateway/models/auth_confirm_identifier_type.py
abdm_gateway/models/auth_meta.py
abdm_gateway/models/authentication_mode.py
abdm_gateway/models/care_context.py
abdm_gateway/models/care_context_definition.py
abdm_gateway/models/care_context_representation.py
abdm_gateway/models/certificate_or_key_get_schema.py
abdm_gateway/models/certs.py
abdm_gateway/models/consent.py
abdm_gateway/models/consent_acknowledgement.py
abdm_gateway/models/consent_artefact_reference.py
abdm_gateway/models/consent_artefact_response.py
abdm_gateway/models/consent_artefact_response_consent.py
abdm_gateway/models/consent_artefact_response_consent_consent_detail.py
abdm_gateway/models/consent_artefact_response_consent_consent_detail_consent_manager.py
abdm_gateway/models/consent_fetch_request.py
abdm_gateway/models/consent_manager_patient_id.py
abdm_gateway/models/consent_request.py
abdm_gateway/models/consent_request_consent.py
abdm_gateway/models/consent_request_consent_hiu.py
abdm_gateway/models/consent_request_consent_patient.py
abdm_gateway/models/consent_request_init_response.py
abdm_gateway/models/consent_request_init_response_consent_request.py
abdm_gateway-1.0.0.dist-info/METADATA
abdm_gateway-1.0.0.dist-info/WHEEL
abdm_gateway-1.0.0.dist-info/RECORD
