Metadata-Version: 2.1
Name: abdm_gateway
Version: 1.0.0
Summary: Gateway
Home-page: https://github.com/GIT_USER_ID/GIT_REPO_ID
License: NoLicense
Keywords: OpenAPI,OpenAPI-Generator,Gateway
Author: OpenAPI Generator Community
Author-email: team@openapitools.org
Requires-Python: >=3.7,<4.0
Classifier: License :: Other/Proprietary License
Classifier: Programming Language :: Python :: 3
Classifier: Programming Language :: Python :: 3.7
Classifier: Programming Language :: Python :: 3.8
Classifier: Programming Language :: Python :: 3.9
Classifier: Programming Language :: Python :: 3.10
Classifier: Programming Language :: Python :: 3.11
Classifier: Programming Language :: Python :: 3.12
Requires-Dist: pydantic (>=2)
Requires-Dist: python-dateutil (>=2.8.2)
Requires-Dist: typing-extensions (>=4.7.1)
Requires-Dist: urllib3 (>=1.25.3)
Project-URL: Repository, https://github.com/GIT_USER_ID/GIT_REPO_ID
